resource_pool.py
resource_pool-0.2.0.dist-info/DESCRIPTION.rst
resource_pool-0.2.0.dist-info/METADATA
resource_pool-0.2.0.dist-info/RECORD
resource_pool-0.2.0.dist-info/WHEEL
resource_pool-0.2.0.dist-info/metadata.json
resource_pool-0.2.0.dist-info/top_level.txt
