Metadata-Version: 2.0
Name: resource-pool
Version: 0.2.0
Summary: A generic resource pool implementation.
Home-page: UNKNOWN
Author: UNKNOWN
Author-email: UNKNOWN
License: UNKNOWN
Platform: UNKNOWN
Requires-Python: >=3.5
